assets/logo.jpg
thundra/__init__.py
thundra/__main__.py
thundra/agents.py
thundra/button/__init__.py
thundra/button/registry.py
thundra/button/types.py
thundra/button/v1.py
thundra/button/v2.py
thundra/chain.py
thundra/cli.py
thundra/command.py
thundra/config.py
thundra/core/__init__.py
thundra/core/graph.py
thundra/core/llm.py
thundra/core/memory.py
thundra/evaluater.py
thundra/middleware.py
thundra/plugins.py
thundra/profiler/__init__.py
thundra/storage/__init__.py
thundra/storage/file.py
thundra/templates/.gitignore
thundra/templates/README.md
thundra/templates/app/agents/base.py
thundra/templates/app/agents/yt.py
thundra/templates/app/app.py
thundra/templates/app/commands/base.py
thundra/templates/app/commands/yt.py
thundra/templates/app/middleware/auto_save_media.py
thundra/templates/thundra.toml
thundra/test.py
thundra/types.py
thundra/utils.py
thundra/workdir.py
thundra_ai-0.1.6.dist-info/LICENSE
thundra_ai-0.1.6.dist-info/METADATA
thundra_ai-0.1.6.dist-info/WHEEL
thundra_ai-0.1.6.dist-info/entry_points.txt
thundra_ai-0.1.6.dist-info/RECORD
